gofile/__init__.py
gofile/client.py
gofile_client-1.0.1.dist-info/LICENSE
gofile_client-1.0.1.dist-info/METADATA
gofile_client-1.0.1.dist-info/WHEEL
gofile_client-1.0.1.dist-info/top_level.txt
gofile_client-1.0.1.dist-info/RECORD
