Metadata-Version: 2.1
Name: gofile-client
Version: 1.0.1
Summary: Interact with the gofile.io API
Home-page: https://github.com/rdnkarchiver/gofile-client
Author: rdnkarchiver
Author-email: rdnkarchiver@protonmail.com
License: UNKNOWN
Project-URL: Bug Tracker, https://github.com/rdnkarchiver/gofile-client/issues
Platform: UNKNOWN
Classifier: Programming Language :: Python :: 3
Classifier: License :: OSI Approved :: Apache Software License
Classifier: Operating System :: OS Independent
License-File: LICENSE
Requires-Dist: requests
